setup.py
skdesign/__init__.py
skdesign/version.py
skdesign.egg-info/PKG-INFO
skdesign.egg-info/SOURCES.txt
skdesign.egg-info/dependency_links.txt
skdesign.egg-info/top_level.txt