Metadata-Version: 1.0
Name: skdesign
Version: 0.1
Summary: Tools for Statistical Study Design
Home-page: http://github.com/louden/skdesign
Author: Christopher Louden
Author-email: chris@loudenanalytics.com
License: BSD
Keywords: randomization study design trial
Platform: UNKNOWN
